tigrbl_auth/README.md
tigrbl_auth/__init__.py
tigrbl_auth/adapters/__init__.py
tigrbl_auth/adapters/local_adapter.py
tigrbl_auth/adapters/remote_adapter.py
tigrbl_auth/app.py
tigrbl_auth/backends.py
tigrbl_auth/crypto.py
tigrbl_auth/db.py
tigrbl_auth/deps.py
tigrbl_auth/errors.py
tigrbl_auth/fastapi_deps.py
tigrbl_auth/jwtoken.py
tigrbl_auth/oidc_discovery.py
tigrbl_auth/oidc_id_token.py
tigrbl_auth/oidc_userinfo.py
tigrbl_auth/orm/__init__.py
tigrbl_auth/orm/api_key.py
tigrbl_auth/orm/auth_code.py
tigrbl_auth/orm/auth_session.py
tigrbl_auth/orm/client.py
tigrbl_auth/orm/device_code.py
tigrbl_auth/orm/pushed_authorization_request.py
tigrbl_auth/orm/revoked_token.py
tigrbl_auth/orm/service.py
tigrbl_auth/orm/service_key.py
tigrbl_auth/orm/tenant.py
tigrbl_auth/orm/user.py
tigrbl_auth/principal_ctx.py
tigrbl_auth/rfc6749.py
tigrbl_auth/rfc6750.py
tigrbl_auth/rfc7009.py
tigrbl_auth/rfc7515.py
tigrbl_auth/rfc7516.py
tigrbl_auth/rfc7517.py
tigrbl_auth/rfc7518.py
tigrbl_auth/rfc7519.py
tigrbl_auth/rfc7520.py
tigrbl_auth/rfc7521.py
tigrbl_auth/rfc7523.py
tigrbl_auth/rfc7591.py
tigrbl_auth/rfc7592.py
tigrbl_auth/rfc7636_pkce.py
tigrbl_auth/rfc7638.py
tigrbl_auth/rfc7662.py
tigrbl_auth/rfc7800.py
tigrbl_auth/rfc7952.py
tigrbl_auth/rfc8037.py
tigrbl_auth/rfc8176.py
tigrbl_auth/rfc8252.py
tigrbl_auth/rfc8291.py
tigrbl_auth/rfc8414.py
tigrbl_auth/rfc8414_metadata.py
tigrbl_auth/rfc8523.py
tigrbl_auth/rfc8628.py
tigrbl_auth/rfc8693.py
tigrbl_auth/rfc8705.py
tigrbl_auth/rfc8707.py
tigrbl_auth/rfc8725.py
tigrbl_auth/rfc8812.py
tigrbl_auth/rfc8932.py
tigrbl_auth/rfc9068.py
tigrbl_auth/rfc9101.py
tigrbl_auth/rfc9126.py
tigrbl_auth/rfc9207.py
tigrbl_auth/rfc9396.py
tigrbl_auth/rfc9449_dpop.py
tigrbl_auth/routers/__init__.py
tigrbl_auth/routers/auth_flows.py
tigrbl_auth/routers/authz/__init__.py
tigrbl_auth/routers/authz/oidc.py
tigrbl_auth/routers/authz/rfc6749.py
tigrbl_auth/routers/authz/rfc7662.py
tigrbl_auth/routers/schemas.py
tigrbl_auth/routers/shared.py
tigrbl_auth-0.3.0.dev4.dist-info/LICENSE
tigrbl_auth-0.3.0.dev4.dist-info/METADATA
tigrbl_auth-0.3.0.dev4.dist-info/WHEEL
tigrbl_auth-0.3.0.dev4.dist-info/RECORD
