Metadata-Version: 2.3
Name: tigrbl-auth
Version: 0.3.0.dev4
Summary: A Tigrbl Multi‑tenant OpenID‑Connect / OAuth2 Identity‑Provider server by Swarmauri.
License: Apache-2.0
Keywords: oidc,oauth2,fastapi,identity-provider,jwks,jwt
Author: Swarmauri Team
Author-email: support@swarmauri.com
Requires-Python: >=3.10,<3.13
Classifier: License :: OSI Approved :: Apache Software License
Classifier: Development Status :: 3 - Alpha
Classifier: Programming Language :: Python :: 3.10
Classifier: Programming Language :: Python :: 3.11
Classifier: Programming Language :: Python :: 3.12
Requires-Dist: aiosqlite (>=0.19,<1.0)
Requires-Dist: asyncpg (>=0.29,<1.0)
Requires-Dist: bcrypt (>=4.1)
Requires-Dist: fastapi (>=0.111)
Requires-Dist: httpx (>=0.27)
Requires-Dist: pydantic (>=2.7,<3.0)
Requires-Dist: pydantic-settings (>=2.2,<3.0)
Requires-Dist: pydantic[email]
Requires-Dist: python-multipart (>=0.0.9)
Requires-Dist: sqlalchemy[asyncio] (>=2.0,<3.0)
Requires-Dist: swarmauri_base
Requires-Dist: swarmauri_core
Requires-Dist: swarmauri_crypto_jwe
Requires-Dist: swarmauri_keyprovider_file
Requires-Dist: swarmauri_keyprovider_local
Requires-Dist: swarmauri_signing_ed25519
Requires-Dist: swarmauri_signing_jws
Requires-Dist: swarmauri_standard
Requires-Dist: swarmauri_tokens_jwt
Requires-Dist: tigrbl
Requires-Dist: uvicorn[standard] (>=0.29)
